Metadata-Version: 2.1
Name: load-following-decision
Version: 0.1.0
Summary: This package performs an economic analysis of a micro-CHP system paired with thermal energy storage
Home-page: https://github.com/SoftwareDevEngResearch/load_following_decision
Author: Christopher Curl
Author-email: curlc@oregonstate.edu
License: MIT License
Platform: UNKNOWN
Classifier: Programming Language :: Python :: 3
Classifier: Programming Language :: Python :: 3.7
Classifier: License :: OSI Approved :: MIT License
Classifier: Operating System :: OS Independent
Classifier: Intended Audience :: Science/Research
Classifier: Natural Language :: English
Requires-Python: >=3.7
License-File: LICENSE
Requires-Dist: pandas (>=1.3.5)
Requires-Dist: PyYAML (>=6.0)
Requires-Dist: pytest (>=7.0.1)
Requires-Dist: tabulate (>=0.8.9)
Requires-Dist: matplotlib (>=3.5.1)
Requires-Dist: pint (>=0.18)
